toga_win32/__init__.py
toga_win32/app.py
toga_win32/window.py
toga_win32/libs/__init__.py
toga_win32/libs/constants.py
toga_win32/libs/debug.py
toga_win32/libs/gdi32.py
toga_win32/libs/kernel32.py
toga_win32/libs/key.py
toga_win32/libs/types.py
toga_win32/libs/user32.py
toga_win32/widgets/__init__.py
toga_win32/widgets/base.py
toga_win32/widgets/button.py
toga_win32/widgets/container.py
toga_win32-0.1.2.dist-info/DESCRIPTION.rst
toga_win32-0.1.2.dist-info/METADATA
toga_win32-0.1.2.dist-info/metadata.json
toga_win32-0.1.2.dist-info/RECORD
toga_win32-0.1.2.dist-info/top_level.txt
toga_win32-0.1.2.dist-info/WHEEL
